[
  {
    "ApiId": "/providers/microsoft.powerapps/apis/shared_sharepointonline",
    "CdpRevision": {
      "BaseUrl": "/",
      "LastChangedTimeString": "2025-07-31T18:56:00.2370000Z",
      "RevisionNumber": 1
    },
    "ConnectedDataSourceInfoNameMapping": {
      "{Attachments}": "Anexos",
      "{Attachments}@odata.type": "{Attachments} ({Attachments}@odata.type)",
      "{ContentType}": "Tipo de conteúdo",
      "{ContentType}#Id": "Tipo de conteúdo Id",
      "{FilenameWithExtension}": "Nome de arquivo com extensão",
      "{FullPath}": "Caminho Completo",
      "{HasAttachments}": "Tem anexos",
      "{Identifier}": "Identificador",
      "{IsFolder}": "ÉPasta",
      "{Link}": "Link para o item",
      "{ModerationComment}": "Comentários associados à aprovação de conteúdo deste item de lista",
      "{ModerationStatus}": "Status de aprovação de conteúdo",
      "{Name}": "Nome",
      "{Path}": "Caminho da pasta",
      "{Thumbnail}": "Miniatura",
      "{TriggerWindowEndToken}": "Token de Fim da Janela de Acionamento",
      "{TriggerWindowStartToken}": "Token de Início da Janela de Acionamento",
      "{VersionNumber}": "Número da versão",
      "Alguma_x0020_pessoa_x0020_com_x0": "Alguma pessoa com mais de 16 anos na sua casa parou de ir para a escola e tem interesse em voltar a estudar",
      "Alguma_x0020_pessoa_x0020_com_x0#Id": "Alguma pessoa com mais de 16 anos na sua casa parou de ir para a escola e tem interesse em voltar a estudar Id",
      "As_x0020_crian_x00e7_as_x0020_qu": "As crianças que moram na sua casa estão com a vacinação em dia",
      "As_x0020_crian_x00e7_as_x0020_qu#Id": "As crianças que moram na sua casa estão com a vacinação em dia Id",
      "Author": "Criado por",
      "Author#Claims": "Criado por Claims",
      "Bairro": "Bairro",
      "Com_x0020_a_x0020_mudan_x00e7_a_": "Com a mudança para a nova moradia, você acha que irá afetar a sua relação com essa rede",
      "Com_x0020_a_x0020_mudan_x00e7_a_#Id": "Com a mudança para a nova moradia, você acha que irá afetar a sua relação com essa rede Id",
      "ComplianceAssetId": "ID de Ativo de Conformidade",
      "CPF": "CPF",
      "Created": "Criado",
      "Data_Nascimento": "Data_Nascimento",
      "Destas_x0020_pessoas_x0020_gr_x0": "Destas pessoas grávidas, alguma é menor de idade",
      "Destas_x0020_pessoas_x0020_gr_x0#Id": "Destas pessoas grávidas, alguma é menor de idade Id",
      "Destas_x0020_pessoas_x0020_gr_x00": "Destas pessoas grávidas, quantas são menores de idade",
      "Editor": "Modificado por",
      "Editor#Claims": "Modificado por Claims",
      "Em_x0020_rela_x00e7__x00e3_o_x00": "Em relação ao lixo doméstico, você costuma separar os resíduos recicláveis dos orgânicos",
      "Em_x0020_rela_x00e7__x00e3_o_x00#Id": "Em relação ao lixo doméstico, você costuma separar os resíduos recicláveis dos orgânicos Id",
      "Em_x0020_rela_x00e7__x00e3_o_x000": "Em relação a sua atual moradia, você possui uma rede de apoio próxima",
      "Em_x0020_rela_x00e7__x00e3_o_x000#Id": "Em relação a sua atual moradia, você possui uma rede de apoio próxima Id",
      "Em_x0020_rela_x00e7__x00e3_o_x001": "Em relação a sua atual moradia, você possui qual rede de apoio próxima",
      "Em_x0020_rela_x00e7__x00e3_o_x001#Id": "Em relação a sua atual moradia, você possui qual rede de apoio próxima Id",
      "Em_x0020_rela_x00e7__x00e3_o_x002": "Em relação à nova moradia, o que você acha que vai melhorar na sua condição de vida",
      "Em_x0020_rela_x00e7__x00e3_o_x002#Id": "Em relação à nova moradia, o que você acha que vai melhorar na sua condição de vida Id",
      "Email": "Email",
      "Endereco_Atual": "Endereco_Atual",
      "Est_x00e1__x0020_cadastrado_x002": "Está cadastrado(a) no CadÚnico",
      "Est_x00e1__x0020_cadastrado_x002#Id": "Está cadastrado(a) no CadÚnico Id",
      "Este_x0020_cadastro_x0020_est_x0": "Este cadastro está atualizado",
      "Este_x0020_cadastro_x0020_est_x0#Id": "Este cadastro está atualizado Id",
      "H_x00e1__x0020_quantas_x0020_pes": "Há quantas pessoas adultas morando com você, de 25 a 59 anos? (incluindo o/a respondente)",
      "ID": "ID",
      "latitude": "latitude",
      "longitude": "longitude",
      "Modified": "Modificado",
      "Nome_Completo": "Nome_Completo",
      "Nucleo": "Nucleo",
      "OData__ColorTag": "Pressione Delete para excluir o ícone.",
      "OData__x0020_Voc_x00ea__x0020_j_x00e1_": " Você já precisou acessar esse atendimento",
      "OData__x0020_Voc_x00ea__x0020_j_x00e1_#Id": " Você já precisou acessar esse atendimento Id",
      "Os_x0020__x0028_as_x0029__x0020_": "Os (as) adolescentes que moram na sua casa estão com a vacinação em dia",
      "Os_x0020__x0028_as_x0029__x0020_#Id": "Os (as) adolescentes que moram na sua casa estão com a vacinação em dia Id",
      "Quais_x0020_dos_x0020_cursos_x00": "Quais dos cursos abaixo vocês teriam interesse em fazer",
      "Quais_x0020_dos_x0020_cursos_x00#Id": "Quais dos cursos abaixo vocês teriam interesse em fazer Id",
      "Qual_x0020_a_x0020_sua_x0020_dis": "Qual a sua disponibilidade de tempo para fazer algum curso ou oficina",
      "Qual_x0020_a_x0020_sua_x0020_dis#Id": "Qual a sua disponibilidade de tempo para fazer algum curso ou oficina Id",
      "Qual_x0020_a_x0020_sua_x0020_ide": "Qual a sua identidade étnico-racial?",
      "Qual_x0020_a_x0020_sua_x0020_ide#Id": "Qual a sua identidade étnico-racial? Id",
      "Qual_x0020_a_x0020_sua_x0020_ide0": "Qual a sua identidade de gênero?",
      "Qual_x0020_a_x0020_sua_x0020_ide0#Id": "Qual a sua identidade de gênero? Id",
      "Qual_x0020_dessas_x0020_etapas_x": "Qual dessas etapas de ensino gostariam de retomar",
      "Qual_x0020_dessas_x0020_etapas_x#Id": "Qual dessas etapas de ensino gostariam de retomar Id",
      "Quantas_x0020_crian_x00e7_as_x00": "Quantas crianças de 0 a 3 anos?",
      "Quantas_x0020_crian_x00e7_as_x000": "Quantas crianças de 4 a 6 anos?",
      "Quantas_x0020_crian_x00e7_as_x001": "Quantas crianças de 7 a 11 anos?",
      "Quantas_x0020_de_x0020__x0020_4_": "Quantas de  4 a 6 anos? Qual escola?",
      "Quantas_x0020_de_x0020_0_x0020_a": "Quantas de 0 a 3 anos? Qual escola?",
      "Quantas_x0020_de_x0020_7_x0020_a": "Quantas de 7 a 11 anos? Qual escola?",
      "Quantas_x0020_pessoas_x0020__x00": "Quantas pessoas (contando com você) moram permanentemente na sua residência?",
      "Quantas_x0020_pessoas_x0020_com_": "Quantas pessoas com deficiência morando com você",
      "Quantas_x0020_pessoas_x0020_na_x": "Quantas pessoas na sua casa têm interesse em fazer cursos profissionalizantes",
      "Quantos_x0028_as_x0029__x0020_de": "Quantos(as) de 12 a 14 anos e Qual escola",
      "Quantos_x0028_as_x0029__x0020_de0": "Quantos(as) de 15 a 16 anos e Qual escola",
      "Quantos_x0028_as_x0029__x0020_de1": "Quantos(as) de 17 a 18 anos e Qual escola",
      "Quantos_x0028_as_x0029__x0020_de2": "Quantos(as) de 60 a 79 anos",
      "Quantos_x0028_as_x0029__x0020_de3": "Quantos(as) de mais de 80 anos",
      "Quem_x0020_faz_x0020_parte_x0020": "Quem faz parte da sua rede de apoio atualmente",
      "Quem_x0020_faz_x0020_parte_x0020#Id": "Quem faz parte da sua rede de apoio atualmente Id",
      "Representatividade": "Representatividade",
      "Representatividade#Id": "Representatividade Id",
      "Se_x0020_sim_x002c__x0020_confor": "Se sim, conforme a faixa etária, estão frequentando a escola",
      "Se_x0020_sim_x002c__x0020_confor#Id": "Se sim, conforme a faixa etária, estão frequentando a escola Id",
      "Se_x0020_sim_x002c__x0020_Qual_x": "Se sim, Qual deficiência",
      "Se_x0020_sim_x002c__x0020_Qual_x#Id": "Se sim, Qual deficiência Id",
      "Se_x0020_sim_x002c__x0020_Qual_x@odata.type": "Se_x0020_sim_x002c__x0020_Qual_x (Se_x0020_sim_x002c__x0020_Qual_x@odata.type)",
      "Se_x0020_sim_x002c_conforme_x0025": "Se sim,conforme a faixa etária, estão frequentando a escola",
      "Se_x0020_sim_x002c_conforme_x0025#Id": "Se sim,conforme a faixa etária, estão frequentando a escola Id",
      "Ser_x00e1__x0020_necess_x00e1_ri": "Será necessário mudar de escola após a mudança de moradia",
      "Ser_x00e1__x0020_necess_x00e1_ri#Id": "Será necessário mudar de escola após a mudança de moradia Id",
      "Sesim_x002c_equipamentop_x00fa_b": "Se sim, equipamento público de saúde Especifico?",
      "Sesim_x002c_qualEquipamentop_x00": "Se sim, qual Equipamento público social?",
      "SetemAdolescente_x002e_qualescol": "Se tem Adolescente. qual escola?",
      "SetemCrian_x00e7_a_x002e_qualesc": "Se tem Criança. qual escola?",
      "Telefone": "Telefone",
      "Tem_x0020_adolescentes_x0020_mor": "Tem adolescentes morando com você",
      "Tem_x0020_adolescentes_x0020_mor#Id": "Tem adolescentes morando com você Id",
      "Tem_x0020_adolescentes_x0020_mor0": "Tem adolescentes morando com você Quantos(as) de 12 a 14 anos",
      "Tem_x0020_adolescentes_x0020_mor1": "Tem adolescentes morando com você Quantos(as) de 15 a 16 anos",
      "Tem_x0020_adolescentes_x0020_mor2": "Tem adolescentes morando com você Quantos(as) de 17 a 18 anos",
      "Tem_x0020_alguma_x0020_pessoa_x0": "Tem alguma pessoa grávida que mora com você",
      "Tem_x0020_alguma_x0020_pessoa_x0#Id": "Tem alguma pessoa grávida que mora com você Id",
      "Tem_x0020_crian_x00e7_as_x0020_m5": "Tem crianças morando com você",
      "Tem_x0020_crian_x00e7_as_x0020_m5#Id": "Tem crianças morando com você Id",
      "Tem_x0020_pessoas_x0020_com_x002": "Tem pessoas com deficiência morando com você",
      "Tem_x0020_pessoas_x0020_com_x002#Id": "Tem pessoas com deficiência morando com você Id",
      "Tem_x0020_pessoas_x0020_idosas_x0": "Tem pessoas idosas morando com você",
      "Tem_x0020_pessoas_x0020_idosas_x0#Id": "Tem pessoas idosas morando com você Id",
      "Tem_x0020_quantas_x0020_pessoas_": "Tem quantas pessoas grávidas que mora com você",
      "Title": "Título",
      "Voc_x00ea__x0020_conhece_x0020_o": "Você conhece o número de telefone para onde pode ligar em casos de violência doméstica",
      "Voc_x00ea__x0020_conhece_x0020_o#Id": "Você conhece o número de telefone para onde pode ligar em casos de violência doméstica Id",
      "Voc_x00ea__x0020_conhece_x0020_o0": "Você conhece o território onde irá morar",
      "Voc_x00ea__x0020_conhece_x0020_o0#Id": "Você conhece o território onde irá morar Id",
      "Voc_x00ea__x0020_frequenta_x0020": "Você frequenta algum equipamento público de cultura",
      "Voc_x00ea__x0020_frequenta_x0020#Id": "Você frequenta algum equipamento público de cultura Id",
      "Voc_x00ea__x0020_frequenta_x00200": "Você frequenta qual equipamento público de cultura",
      "Voc_x00ea__x0020_frequenta_x00200#Id": "Você frequenta qual equipamento público de cultura Id",
      "Voc_x00ea__x0020_ou_x0020_algu_x": "Você ou alguém da sua família está fazendo acompanhamento frequente em algum equipamento público de saúde",
      "Voc_x00ea__x0020_ou_x0020_algu_x#Id": "Você ou alguém da sua família está fazendo acompanhamento frequente em algum equipamento público de saúde Id",
      "Voc_x00ea__x0020_ou_x0020_algu_x0": "Você ou alguém da sua família está fazendo acompanhamento frequente em qual equipamento público de saúde",
      "Voc_x00ea__x0020_ou_x0020_algu_x0#Id": "Você ou alguém da sua família está fazendo acompanhamento frequente em qual equipamento público de saúde Id",
      "Voc_x00ea__x0020_ou_x0020_algu_x1": "Você ou alguém da sua família está sendo acompanhado(a) por algum equipamento público social",
      "Voc_x00ea__x0020_ou_x0020_algu_x1#Id": "Você ou alguém da sua família está sendo acompanhado(a) por algum equipamento público social Id",
      "Voc_x00ea__x0020_ou_x0020_algu_x2": "Você ou alguém da sua família está sendo acompanhado(a) por qual equipamento público social",
      "Voc_x00ea__x0020_ou_x0020_algu_x2#Id": "Você ou alguém da sua família está sendo acompanhado(a) por qual equipamento público social Id",
      "Voc_x00ea__x0020_ou_x0020_algu_x3": "Você ou alguém da sua família recebe algum benefício social?",
      "Voc_x00ea__x0020_ou_x0020_algu_x3#Id": "Você ou alguém da sua família recebe algum benefício social? Id",
      "Voc_x00ea__x0020_ou_x0020_algu_x4": "Você ou alguém da sua família recebe qual benefício social?",
      "Voc_x00ea__x0020_ou_x0020_algu_x4#Id": "Você ou alguém da sua família recebe qual benefício social? Id",
      "Voc_x00ea__x0020_ou_x0020_algum_": "Você ou algum membro de sua família faz tratamento para alguma questão de saúde crônica",
      "Voc_x00ea__x0020_ou_x0020_algum_#Id": "Você ou algum membro de sua família faz tratamento para alguma questão de saúde crônica Id",
      "Voc_x00ea__x0020_ou_x0020_algum_0": "Você ou algum membro de sua família faz tratamento para qual questão de saúde crônica",
      "Voc_x00ea__x0020_ou_x0020_algum_0#Id": "Você ou algum membro de sua família faz tratamento para qual questão de saúde crônica Id",
      "Voc_x00ea__x0020_participa_x0020": "Você participa de algum evento ou manifestação cultural na região onde você mora",
      "Voc_x00ea__x0020_participa_x0020#Id": "Você participa de algum evento ou manifestação cultural na região onde você mora Id",
      "Voc_x00ea__x0020_participa_x00200": "Você participa de qual evento ou manifestação cultural na região onde você mora",
      "Voc_x00ea__x0020_possui_x0020_an": "Você possui animais animais domésticos",
      "Voc_x00ea__x0020_possui_x0020_an#Id": "Você possui animais animais domésticos Id",
      "Voc_x00ea__x0020_tem_x0020_inter": "Você tem interesse em fazer parte do grupo de administração do condomínio (Corpo Diretivo)",
      "Voc_x00ea__x0020_tem_x0020_inter#Id": "Você tem interesse em fazer parte do grupo de administração do condomínio (Corpo Diretivo) Id",
      "Voc_x00ea_possuiumarededeapoiopr": "Você possui uma rede de apoio próxima a sua futura moradia? ",
      "Voc_x00ea_possuiumarededeapoiopr#Id": "Você possui uma rede de apoio próxima a sua futura moradia?  Id"
    },
    "DatasetName": "https://boninengenharialtda.sharepoint.com/sites/BANCOURBHIS",
    "EncodeDataset": true,
    "IsSampleData": false,
    "IsWritable": true,
    "Name": "dbPesquisaSocioEconomica",
    "Type": "ConnectedDataSourceInfo"
  }
]